empty_files/__init__.py
empty_files/empty_files.py
empty_files/version.py
empty_files-0.0.4.dist-info/LICENSE
empty_files-0.0.4.dist-info/METADATA
empty_files-0.0.4.dist-info/WHEEL
empty_files-0.0.4.dist-info/top_level.txt
empty_files-0.0.4.dist-info/RECORD
